{
  "generatedAt": "2026-06-02T23:11:24Z",
  "repositories": {
    "CellProtocol": {
      "branch": "main",
      "commitDate": "2026-05-31T21:56:31+02:00",
      "head": "23167bd9b286ba3b5e30472532ca4a454b435d37",
      "remote": "https://github.com/Digipomps/CellProtocol",
      "repository": "Digipomps/CellProtocol",
      "status": "available"
    },
    "CellScaffold": {
      "branch": "main",
      "commitDate": "2026-05-20T14:25:47+02:00",
      "head": "79e7b5d03a83209fe0742fb4f4909d2e36de5b9e",
      "remote": "git@github.com:Digipomps/CellScaffold.git",
      "repository": "Digipomps/CellScaffold",
      "status": "available"
    }
  },
  "schemaVersion": "pycellprotocol.upstream-lock.v1"
}
